chronosphere/__init__.py
chronosphere/show.py
chronosphere-0.0.1.dist-info/LICENSE
chronosphere-0.0.1.dist-info/METADATA
chronosphere-0.0.1.dist-info/WHEEL
chronosphere-0.0.1.dist-info/top_level.txt
chronosphere-0.0.1.dist-info/RECORD
